russianCVparser/LICENSE
russianCVparser/README.md
russianCVparser/__init__.py
russianCVparser/requirements.txt
russianCVparser/try.py
russianCVparser/cvparser/__init__.py
russianCVparser/cvparser/document.py
russianCVparser/cvparser/education.py
russianCVparser/cvparser/helpers.py
russianCVparser/cvparser/hobby.py
russianCVparser/cvparser/nlparser.py
russianCVparser/cvparser/socdem.py
russianCVparser/cvparser/workplace.py
russianCVparser/cvparser/dicts/VUZY.txt
russianCVparser/cvparser/dicts/occupations.txt
russianCVparser/cvparser/dicts/specs_only.txt
russianCVparser-1.1.dist-info/METADATA
russianCVparser-1.1.dist-info/WHEEL
russianCVparser-1.1.dist-info/top_level.txt
russianCVparser-1.1.dist-info/RECORD
