Metadata-Version: 2.1
Name: russianCVparser
Version: 1.1
Summary: Parser for CV in russian language. Supported formats: pdf, txt, docx
Home-page: UNKNOWN
Author-email: onsunday1703@gmail.com
License: UNKNOWN
Platform: UNKNOWN
Classifier: Programming Language :: Python :: 3
Classifier: License :: OSI Approved :: MIT License
Classifier: Operating System :: OS Independent
Requires-Python: >=3.6
Requires-Dist: natasha
Requires-Dist: pdfminer.six
Requires-Dist: docx2txt
